jupyterlab_lsstquery/__init__.py
jupyterlab_lsstquery/handlers.py
jupyterlab_lsstquery-2.0.0.dist-info/LICENSE
jupyterlab_lsstquery-2.0.0.dist-info/METADATA
jupyterlab_lsstquery-2.0.0.dist-info/WHEEL
jupyterlab_lsstquery-2.0.0.dist-info/top_level.txt
jupyterlab_lsstquery-2.0.0.dist-info/RECORD
