Metadata-Version: 2.1
Name: jupyterlab-lsstquery
Version: 2.0.0
Summary: UNKNOWN
Home-page: UNKNOWN
Author: UNKNOWN
Author-email: UNKNOWN
License: UNKNOWN
Platform: UNKNOWN
Requires-Dist: notebook
